swolfpy_inputdata/AD_Input.py
swolfpy_inputdata/AnF_Input.py
swolfpy_inputdata/COM_Col_Input.py
swolfpy_inputdata/CommonData.py
swolfpy_inputdata/Comp_Input.py
swolfpy_inputdata/GC_Input.py
swolfpy_inputdata/HC_Input.py
swolfpy_inputdata/InputData.py
swolfpy_inputdata/LF_Input.py
swolfpy_inputdata/MC.py
swolfpy_inputdata/MF_Col_Input.py
swolfpy_inputdata/RDF_Input.py
swolfpy_inputdata/Reproc_Input.py
swolfpy_inputdata/SF_Col_Input.py
swolfpy_inputdata/SS_MRF_Input.py
swolfpy_inputdata/TS_Input.py
swolfpy_inputdata/Technosphere_Input.py
swolfpy_inputdata/WTE_Input.py
swolfpy_inputdata/__init__.py
swolfpy_inputdata/Ecospold2/__init__.py
swolfpy_inputdata/data/AD_Input.csv
swolfpy_inputdata/data/AD_Input_MaterialDependent.csv
swolfpy_inputdata/data/AnF_Input.csv
swolfpy_inputdata/data/AnF_Input_MaterialDependent.csv
swolfpy_inputdata/data/COM_Col_Input.csv
swolfpy_inputdata/data/COM_Col_Input_MaterialDependent.csv
swolfpy_inputdata/data/CommonData.csv
swolfpy_inputdata/data/Comp_Input.csv
swolfpy_inputdata/data/Comp_Input_MaterialDependent.csv
swolfpy_inputdata/data/Distance.csv
swolfpy_inputdata/data/GC_Input.csv
swolfpy_inputdata/data/GC_Input_MaterialDependent.csv
swolfpy_inputdata/data/HC_Input.csv
swolfpy_inputdata/data/HC_Input_MaterialDependent.csv
swolfpy_inputdata/data/LF_GasColPlan.csv
swolfpy_inputdata/data/LF_Gas_emission_factors.csv
swolfpy_inputdata/data/LF_Input.csv
swolfpy_inputdata/data/LF_Input_MaterialDependent.csv
swolfpy_inputdata/data/LF_Leachate_Quality.csv
swolfpy_inputdata/data/MF_Col_Input.csv
swolfpy_inputdata/data/MF_Col_Input_MaterialDependent.csv
swolfpy_inputdata/data/Material properties.csv
swolfpy_inputdata/data/RDF_Input.csv
swolfpy_inputdata/data/RDF_Input_MaterialDependent.csv
swolfpy_inputdata/data/References.csv
swolfpy_inputdata/data/Reprocessing_Input.csv
swolfpy_inputdata/data/SF_Col_Input.csv
swolfpy_inputdata/data/SF_Col_Input_MaterialDependent.csv
swolfpy_inputdata/data/SS_MRF_Input.csv
swolfpy_inputdata-1.1.0.dist-info/AUTHORS.rst
swolfpy_inputdata-1.1.0.dist-info/LICENSE.md
swolfpy_inputdata-1.1.0.dist-info/METADATA
swolfpy_inputdata-1.1.0.dist-info/WHEEL
swolfpy_inputdata-1.1.0.dist-info/top_level.txt
swolfpy_inputdata-1.1.0.dist-info/RECORD
