Metadata-Version: 2.1
Name: swolfpy-inputdata
Version: 1.1.0
Summary: Input data for swolfpy's life-cycle process models (swolfpy_inputdata).
Author-email: Mojtaba Sardarmehni <msardar2@alumni.ncsu.edu>
Maintainer-email: Mojtaba Sardarmehni <msardar2@alumni.ncsu.edu>
License: GNU GENERAL PUBLIC LICENSE V2
Project-URL: Homepage, https://swolfpy-project.github.io/
Project-URL: Documentation, https://swolfpy.readthedocs.io/en/latest/
Project-URL: Source Code, https://github.com/SwolfPy-Project/swolfpy-inputdata
Keywords: LCA,solid_waste,waste_management,swolfpy,brightway2
Classifier: Development Status :: 5 - Production/Stable
Classifier: Intended Audience :: Education
Classifier: Intended Audience :: Science/Research
Classifier: License :: OSI Approved :: GNU General Public License v2 (GPLv2)
Classifier: Natural Language :: English
Classifier: Programming Language :: Python :: 3.9
Classifier: Operating System :: MacOS :: MacOS X
Classifier: Operating System :: Microsoft :: Windows
Classifier: Topic :: Scientific/Engineering :: Information Analysis
Classifier: Topic :: Scientific/Engineering :: Mathematics
Classifier: Topic :: Scientific/Engineering :: Visualization
Classifier: Natural Language :: English
Requires-Python: >=3.9
License-File: LICENSE.md
License-File: AUTHORS.rst
Requires-Dist: coverage
Requires-Dist: jupyter
Requires-Dist: pandas
Requires-Dist: pre-commit
Requires-Dist: pylint
Requires-Dist: pytest
Requires-Dist: pytest-cov
Requires-Dist: pytest-flake8
Requires-Dist: stats-arrays
Requires-Dist: xlrd (==1.2.0)
